Metadata-Version: 2.1
Name: calista
Version: 0.3.3
Summary: Comprehensive Python package designed to simplify data quality checks across multiple platforms
License: UNKNOWN
Project-URL: Repository, https://github.com/Aubay-Data-AI/calista
Platform: UNKNOWN
Classifier: Programming Language :: Python :: 3
Classifier: Operating System :: OS Independent
Requires-Python: >=3.9.5
License-File: LICENSE
Requires-Dist: pandas>=2.2.0
Requires-Dist: pyarrow>=15.0.0
Requires-Dist: pydantic>=2.8.0
Requires-Dist: overrides>=7.7.0
Requires-Dist: schema>=0.7.5
Requires-Dist: python-dotenv>=1.0.1
Requires-Dist: polars<1.7,>=0.20.21
Provides-Extra: bigquery
Requires-Dist: sqlalchemy>=2.0.29; extra == "bigquery"
Requires-Dist: sqlalchemy-bigquery>=1.11.0; extra == "bigquery"
Provides-Extra: snowflake
Requires-Dist: snowflake-snowpark-python>=1.12.1; extra == "snowflake"
Provides-Extra: spark
Requires-Dist: pyspark>=3.5.0; extra == "spark"
Requires-Dist: delta-spark>=3.1.0; extra == "spark"
